{
  "attribution": "© Google",
  "captured_at": "2014-10",
  "fov": 90.0,
  "heading": 270.0,
  "height": 640,
  "id": "google:KgmZNoIb7NvPeKO-A-Mf1Q:h270",
  "is_pano": true,
  "lat": 41.18097892339435,
  "license": "Google Maps Platform Terms of Service / Street View Static API terms",
  "lon": 1.525801471419499,
  "metadata_source_url": "https://maps.googleapis.com/maps/api/streetview/metadata",
  "pano_id": "KgmZNoIb7NvPeKO-A-Mf1Q",
  "pitch": 0.0,
  "provider": "google-street-view",
  "raw_metadata_path": "captures/google_KgmZNoIb7NvPeKO-A-Mf1Q_h270/metadata.raw.json",
  "sequence_id": null,
  "source_url": "https://maps.googleapis.com/maps/api/streetview",
  "width": 640
}
